swag_ares/__init__.py
swag_ares/api_client.py
swag_ares/api_response.py
swag_ares/configuration.py
swag_ares/exceptions.py
swag_ares/py.typed
swag_ares/rest.py
swag_ares/api/__init__.py
swag_ares/api/ciselniky_nazevniky_api.py
swag_ares/api/ekonomicke_subjekty_api.py
swag_ares/api/ekonomicke_subjekty_ceu_api.py
swag_ares/api/ekonomicke_subjekty_notifikace_api.py
swag_ares/api/ekonomicke_subjekty_nrpzs_api.py
swag_ares/api/ekonomicke_subjekty_rcns_api.py
swag_ares/api/ekonomicke_subjekty_res_api.py
swag_ares/api/ekonomicke_subjekty_rpsh_api.py
swag_ares/api/ekonomicke_subjekty_rs_api.py
swag_ares/api/ekonomicke_subjekty_rzp_api.py
swag_ares/api/ekonomicke_subjekty_szr_api.py
swag_ares/api/ekonomicke_subjekty_vr_api.py
swag_ares/api/standardizovane_adresy_api.py
swag_ares/models/__init__.py
swag_ares/models/adresa.py
swag_ares/models/adresa_ares.py
swag_ares/models/adresa_ceu.py
swag_ares/models/adresa_dorucovaci.py
swag_ares/models/adresa_filtr.py
swag_ares/models/adresa_rcns.py
swag_ares/models/adresa_vr.py
swag_ares/models/angazma_clenstvi_vr.py
swag_ares/models/angazma_fyzicka_osoba_vr.py
swag_ares/models/angazma_osoba_vr.py
swag_ares/models/angazma_rcns.py
swag_ares/models/angazovana_osoba.py
swag_ares/models/angazovana_osoba_ceu.py
swag_ares/models/angazovana_osoba_filtr.py
swag_ares/models/angazovana_osoba_nrpzs.py
swag_ares/models/angazovana_osoba_rcns.py
swag_ares/models/angazovana_osoba_rpsh.py
swag_ares/models/angazovana_osoba_rs.py
swag_ares/models/angazovana_osoba_rzp.py
swag_ares/models/angazovana_osoba_szr_zaklad.py
swag_ares/models/angazovany_subjekt_adresa.py
swag_ares/models/angazovany_subjekt_rcns.py
swag_ares/models/angazovany_subjekt_rcns_zaklad.py
swag_ares/models/angazovany_subjekt_rs.py
swag_ares/models/angazovany_subjekt_rzp.py
swag_ares/models/angazovany_subjekt_rzp_zaklad.py
swag_ares/models/chyba.py
swag_ares/models/chyby.py
swag_ares/models/cinnosti_vr.py
swag_ares/models/ciselnik.py
swag_ares/models/ciselniky_nazevnik_seznam.py
swag_ares-0.2.0.dist-info/METADATA
swag_ares-0.2.0.dist-info/WHEEL
swag_ares-0.2.0.dist-info/top_level.txt
swag_ares-0.2.0.dist-info/RECORD
