Metadata-Version: 2.1
Name: swag-ares
Version: 0.2.0
Summary: ARES: REST API - veřejné
Home-page: 
Author: OpenAPI Generator community
Author-email: team@openapitools.org
Keywords: OpenAPI,OpenAPI-Generator,ARES: REST API - veřejné
Requires-Dist: urllib3 <2.1.0,>=1.25.3
Requires-Dist: python-dateutil
Requires-Dist: pydantic >=2
Requires-Dist: typing-extensions >=4.7.1
